tests/__init__.py
tests/test_web_crawling.py
valentinas_p_mod1_atsiskaitymas/__init__.py
valentinas_p_mod1_atsiskaitymas/web_crawling.py
valentinas_p_mod1_atsiskaitymas-0.11.dist-info/METADATA
valentinas_p_mod1_atsiskaitymas-0.11.dist-info/WHEEL
valentinas_p_mod1_atsiskaitymas-0.11.dist-info/top_level.txt
valentinas_p_mod1_atsiskaitymas-0.11.dist-info/RECORD
