Metadata-Version: 2.1
Name: valentinas-p_mod1-atsiskaitymas
Version: 0.11
Home-page: https://github.com/ValentinasPopov/valentinas-p-mod1-atsiskaitymas/tree/master/valentinas_p_mod1_atsiskaitymas
Author: Valentinas Popov
Requires-Python: >=3.10
Requires-Dist: requests==2.32.3
Requires-Dist: lxml>=5.3.0
